tian_core/__init__.py
tian_core/bus.py
tian_core/command.py
tian_core/common.py
tian_core/config.py
tian_core/entity.py
tian_core/error.py
tian_core/event.py
tian_core/fields.py
tian_core/notification.py
tian_core/response.py
tian_core/setup.py
tian_core/singleton.py
tian_core/sql_builder.py
tian_core/unit_of_work.py
tian_core/view.py
tian_core-0.1.0.dist-info/LICENSE
tian_core-0.1.0.dist-info/METADATA
tian_core-0.1.0.dist-info/WHEEL
tian_core-0.1.0.dist-info/RECORD
